{"trial_id": "d621f06b5df0eace99c73a89d7c16d74", "hyperparameters": {"space": [{"class_name": "Int", "config": {"name": "units", "default": 64, "conditions": [], "min_value": 64, "max_value": 256, "step": 16, "sampling": null}}, {"class_name": "Choice", "config": {"name": "dense_activation", "default": "relu", "conditions": [], "values": ["relu", "tanh", "sigmoid"], "ordered": false}}, {"class_name": "Float", "config": {"name": "dropout", "default": 0.005, "conditions": [], "min_value": 0.0, "max_value": 0.1, "step": 0.01, "sampling": null}}], "values": {"units": 192, "dense_activation": "relu", "dropout": 0.03}}, "metrics": {"metrics": {"loss": {"direction": "min", "observations": [{"value": [0.8821285367012024], "step": 0}]}, "accuracy": {"direction": "max", "observations": [{"value": [0.0], "step": 0}]}, "val_loss": {"direction": "min", "observations": [{"value": [0.9173795878887177], "step": 0}]}, "val_accuracy": {"direction": "max", "observations": [{"value": [0.0], "step": 0}]}}}, "score": 0.8821285367012024, "best_step": 0, "status": "COMPLETED"}